pyerrorreport/__init__.py
pyerrorreport/__main__.py
pyerrorreport-0.1.dist-info/LICENSE
pyerrorreport-0.1.dist-info/METADATA
pyerrorreport-0.1.dist-info/WHEEL
pyerrorreport-0.1.dist-info/top_level.txt
pyerrorreport-0.1.dist-info/RECORD
